{
  "annotations": {
    "list": [
      {
        "builtIn": 1,
        "datasource": {
          "type": "datasource",
          "uid": "grafana"
        },
        "enable": true,
        "hide": true,
        "iconColor": "rgba(0, 211, 255, 1)",
        "name": "Annotations & Alerts",
        "type": "dashboard"
      }
    ]
  },
  "description": "Overview of all numeric PostgreSQL settings using the settings_num metric. One row per setting per collection, setting name stored as tag. Replaces the legacy wide-column 'settings' metric that caused Prometheus label cardinality explosion.",
  "editable": true,
  "fiscalYearStartMonth": 0,
  "graphTooltip": 0,
  "links": [],
  "panels": [
    {
      "collapsed": false,
      "gridPos": {
        "h": 1,
        "w": 24,
        "x": 0,
        "y": 0
      },
      "id": 1,
      "panels": [],
      "title": "Server & Connection",
      "type": "row"
    },
    {
      "datasource": {
        "type": "grafana-postgresql-datasource",
        "uid": "pgwatch-metrics"
      },
      "description": "e.g. 160005 = PG 16.5",
      "fieldConfig": {
        "defaults": {
          "color": {
            "mode": "thresholds"
          },
          "decimals": 0,
          "mappings": [
            {
              "options": {
                "match": "null",
                "result": {
                  "text": "N/A"
                }
              },
              "type": "special"
            }
          ],
          "thresholds": {
            "mode": "absolute",
            "steps": [
              {
                "color": "blue"
              }
            ]
          },
          "unit": "none"
        },
        "overrides": []
      },
      "gridPos": {
        "h": 4,
        "w": 4,
        "x": 0,
        "y": 1
      },
      "hideTimeOverride": true,
      "id": 2,
      "maxDataPoints": 100,
      "options": {
        "colorMode": "value",
        "graphMode": "none",
        "justifyMode": "auto",
        "orientation": "horizontal",
        "percentChangeColorMode": "standard",
        "reduceOptions": {
          "calcs": [
            "lastNotNull"
          ],
          "fields": "",
          "values": false
        },
        "showPercentChange": false,
        "textMode": "auto",
        "wideLayout": true
      },
      "pluginVersion": "12.3.1",
      "targets": [
        {
          "datasource": {
            "type": "grafana-postgresql-datasource",
            "uid": "pgwatch-metrics"
          },
          "format": "table",
          "metricColumn": "none",
          "rawQuery": true,
          "rawSql": "SELECT (data->>'value')::float8 AS value\nFROM settings_num\nWHERE dbname = '$dbname'\n  AND tag_data->>'name' = 'server_version_num'\n  AND $__timeFilter(time)\nORDER BY time DESC LIMIT 1",
          "refId": "A"
        }
      ],
      "timeFrom": "6h",
      "title": "Server Version Num",
      "type": "stat"
    },
    {
      "datasource": {
        "type": "grafana-postgresql-datasource",
        "uid": "pgwatch-metrics"
      },
      "description": "",
      "fieldConfig": {
        "defaults": {
          "color": {
            "mode": "thresholds"
          },
          "decimals": 0,
          "mappings": [
            {
              "options": {
                "match": "null",
                "result": {
                  "text": "N/A"
                }
              },
              "type": "special"
            }
          ],
          "thresholds": {
            "mode": "absolute",
            "steps": [
              {
                "color": "blue"
              }
            ]
          },
          "unit": "short"
        },
        "overrides": []
      },
      "gridPos": {
        "h": 4,
        "w": 4,
        "x": 4,
        "y": 1
      },
      "hideTimeOverride": true,
      "id": 3,
      "maxDataPoints": 100,
      "options": {
        "colorMode": "value",
        "graphMode": "none",
        "justifyMode": "auto",
        "orientation": "horizontal",
        "percentChangeColorMode": "standard",
        "reduceOptions": {
          "calcs": [
            "lastNotNull"
          ],
          "fields": "",
          "values": false
        },
        "showPercentChange": false,
        "textMode": "auto",
        "wideLayout": true
      },
      "pluginVersion": "12.3.1",
      "targets": [
        {
          "datasource": {
            "type": "grafana-postgresql-datasource",
            "uid": "pgwatch-metrics"
          },
          "format": "table",
          "metricColumn": "none",
          "rawQuery": true,
          "rawSql": "SELECT (data->>'value')::float8 AS value\nFROM settings_num\nWHERE dbname = '$dbname'\n  AND tag_data->>'name' = 'max_connections'\n  AND $__timeFilter(time)\nORDER BY time DESC LIMIT 1",
          "refId": "A"
        }
      ],
      "timeFrom": "6h",
      "title": "Max Connections",
      "type": "stat"
    },
    {
      "datasource": {
        "type": "grafana-postgresql-datasource",
        "uid": "pgwatch-metrics"
      },
      "description": "In 8 kB blocks",
      "fieldConfig": {
        "defaults": {
          "color": {
            "mode": "thresholds"
          },
          "decimals": 0,
          "mappings": [
            {
              "options": {
                "match": "null",
                "result": {
                  "text": "N/A"
                }
              },
              "type": "special"
            }
          ],
          "thresholds": {
            "mode": "absolute",
            "steps": [
              {
                "color": "blue"
              }
            ]
          },
          "unit": "short"
        },
        "overrides": []
      },
      "gridPos": {
        "h": 4,
        "w": 4,
        "x": 8,
        "y": 1
      },
      "hideTimeOverride": true,
      "id": 4,
      "maxDataPoints": 100,
      "options": {
        "colorMode": "value",
        "graphMode": "none",
        "justifyMode": "auto",
        "orientation": "horizontal",
        "percentChangeColorMode": "standard",
        "reduceOptions": {
          "calcs": [
            "lastNotNull"
          ],
          "fields": "",
          "values": false
        },
        "showPercentChange": false,
        "textMode": "auto",
        "wideLayout": true
      },
      "pluginVersion": "12.3.1",
      "targets": [
        {
          "datasource": {
            "type": "grafana-postgresql-datasource",
            "uid": "pgwatch-metrics"
          },
          "format": "table",
          "metricColumn": "none",
          "rawQuery": true,
          "rawSql": "SELECT (data->>'value')::float8 AS value\nFROM settings_num\nWHERE dbname = '$dbname'\n  AND tag_data->>'name' = 'shared_buffers'\n  AND $__timeFilter(time)\nORDER BY time DESC LIMIT 1",
          "refId": "A"
        }
      ],
      "timeFrom": "6h",
      "title": "Shared Buffers",
      "type": "stat"
    },
    {
      "datasource": {
        "type": "grafana-postgresql-datasource",
        "uid": "pgwatch-metrics"
      },
      "description": "In kB per sort/hash op",
      "fieldConfig": {
        "defaults": {
          "color": {
            "mode": "thresholds"
          },
          "decimals": 0,
          "mappings": [
            {
              "options": {
                "match": "null",
                "result": {
                  "text": "N/A"
                }
              },
              "type": "special"
            }
          ],
          "thresholds": {
            "mode": "absolute",
            "steps": [
              {
                "color": "blue"
              }
            ]
          },
          "unit": "short"
        },
        "overrides": []
      },
      "gridPos": {
        "h": 4,
        "w": 4,
        "x": 12,
        "y": 1
      },
      "hideTimeOverride": true,
      "id": 5,
      "maxDataPoints": 100,
      "options": {
        "colorMode": "value",
        "graphMode": "none",
        "justifyMode": "auto",
        "orientation": "horizontal",
        "percentChangeColorMode": "standard",
        "reduceOptions": {
          "calcs": [
            "lastNotNull"
          ],
          "fields": "",
          "values": false
        },
        "showPercentChange": false,
        "textMode": "auto",
        "wideLayout": true
      },
      "pluginVersion": "12.3.1",
      "targets": [
        {
          "datasource": {
            "type": "grafana-postgresql-datasource",
            "uid": "pgwatch-metrics"
          },
          "format": "table",
          "metricColumn": "none",
          "rawQuery": true,
          "rawSql": "SELECT (data->>'value')::float8 AS value\nFROM settings_num\nWHERE dbname = '$dbname'\n  AND tag_data->>'name' = 'work_mem'\n  AND $__timeFilter(time)\nORDER BY time DESC LIMIT 1",
          "refId": "A"
        }
      ],
      "timeFrom": "6h",
      "title": "Work Mem",
      "type": "stat"
    },
    {
      "datasource": {
        "type": "grafana-postgresql-datasource",
        "uid": "pgwatch-metrics"
      },
      "description": "In kB (VACUUM, CREATE INDEX)",
      "fieldConfig": {
        "defaults": {
          "color": {
            "mode": "thresholds"
          },
          "decimals": 0,
          "mappings": [
            {
              "options": {
                "match": "null",
                "result": {
                  "text": "N/A"
                }
              },
              "type": "special"
            }
          ],
          "thresholds": {
            "mode": "absolute",
            "steps": [
              {
                "color": "blue"
              }
            ]
          },
          "unit": "short"
        },
        "overrides": []
      },
      "gridPos": {
        "h": 4,
        "w": 4,
        "x": 16,
        "y": 1
      },
      "hideTimeOverride": true,
      "id": 6,
      "maxDataPoints": 100,
      "options": {
        "colorMode": "value",
        "graphMode": "none",
        "justifyMode": "auto",
        "orientation": "horizontal",
        "percentChangeColorMode": "standard",
        "reduceOptions": {
          "calcs": [
            "lastNotNull"
          ],
          "fields": "",
          "values": false
        },
        "showPercentChange": false,
        "textMode": "auto",
        "wideLayout": true
      },
      "pluginVersion": "12.3.1",
      "targets": [
        {
          "datasource": {
            "type": "grafana-postgresql-datasource",
            "uid": "pgwatch-metrics"
          },
          "format": "table",
          "metricColumn": "none",
          "rawQuery": true,
          "rawSql": "SELECT (data->>'value')::float8 AS value\nFROM settings_num\nWHERE dbname = '$dbname'\n  AND tag_data->>'name' = 'maintenance_work_mem'\n  AND $__timeFilter(time)\nORDER BY time DESC LIMIT 1",
          "refId": "A"
        }
      ],
      "timeFrom": "6h",
      "title": "Maintenance Work Mem",
      "type": "stat"
    },
    {
      "datasource": {
        "type": "grafana-postgresql-datasource",
        "uid": "pgwatch-metrics"
      },
      "description": "In 8 kB blocks",
      "fieldConfig": {
        "defaults": {
          "color": {
            "mode": "thresholds"
          },
          "decimals": 0,
          "mappings": [
            {
              "options": {
                "match": "null",
                "result": {
                  "text": "N/A"
                }
              },
              "type": "special"
            }
          ],
          "thresholds": {
            "mode": "absolute",
            "steps": [
              {
                "color": "blue"
              }
            ]
          },
          "unit": "short"
        },
        "overrides": []
      },
      "gridPos": {
        "h": 4,
        "w": 4,
        "x": 20,
        "y": 1
      },
      "hideTimeOverride": true,
      "id": 7,
      "maxDataPoints": 100,
      "options": {
        "colorMode": "value",
        "graphMode": "none",
        "justifyMode": "auto",
        "orientation": "horizontal",
        "percentChangeColorMode": "standard",
        "reduceOptions": {
          "calcs": [
            "lastNotNull"
          ],
          "fields": "",
          "values": false
        },
        "showPercentChange": false,
        "textMode": "auto",
        "wideLayout": true
      },
      "pluginVersion": "12.3.1",
      "targets": [
        {
          "datasource": {
            "type": "grafana-postgresql-datasource",
            "uid": "pgwatch-metrics"
          },
          "format": "table",
          "metricColumn": "none",
          "rawQuery": true,
          "rawSql": "SELECT (data->>'value')::float8 AS value\nFROM settings_num\nWHERE dbname = '$dbname'\n  AND tag_data->>'name' = 'effective_cache_size'\n  AND $__timeFilter(time)\nORDER BY time DESC LIMIT 1",
          "refId": "A"
        }
      ],
      "timeFrom": "6h",
      "title": "Effective Cache Size",
      "type": "stat"
    },
    {
      "collapsed": false,
      "gridPos": {
        "h": 1,
        "w": 24,
        "x": 0,
        "y": 5
      },
      "id": 8,
      "panels": [],
      "title": "Safety / Reliability",
      "type": "row"
    },
    {
      "datasource": {
        "type": "grafana-postgresql-datasource",
        "uid": "pgwatch-metrics"
      },
      "description": "",
      "fieldConfig": {
        "defaults": {
          "color": {
            "mode": "thresholds"
          },
          "decimals": 0,
          "mappings": [
            {
              "options": {
                "0": {
                  "color": "dark-red",
                  "index": 0,
                  "text": "off"
                }
              },
              "type": "value"
            },
            {
              "options": {
                "1": {
                  "color": "dark-green",
                  "index": 1,
                  "text": "on"
                }
              },
              "type": "value"
            },
            {
              "options": {
                "match": "null",
                "result": {
                  "text": "N/A"
                }
              },
              "type": "special"
            }
          ],
          "thresholds": {
            "mode": "absolute",
            "steps": [
              {
                "color": "#d44a3a",
                "value": null
              },
              {
                "color": "#299c46",
                "value": 1
              }
            ]
          },
          "unit": "none"
        },
        "overrides": []
      },
      "gridPos": {
        "h": 4,
        "w": 4,
        "x": 0,
        "y": 6
      },
      "hideTimeOverride": true,
      "id": 9,
      "maxDataPoints": 100,
      "options": {
        "colorMode": "value",
        "graphMode": "none",
        "justifyMode": "auto",
        "orientation": "horizontal",
        "percentChangeColorMode": "standard",
        "reduceOptions": {
          "calcs": [
            "lastNotNull"
          ],
          "fields": "",
          "values": false
        },
        "showPercentChange": false,
        "textMode": "auto",
        "wideLayout": true
      },
      "pluginVersion": "12.3.1",
      "targets": [
        {
          "datasource": {
            "type": "grafana-postgresql-datasource",
            "uid": "pgwatch-metrics"
          },
          "format": "table",
          "metricColumn": "none",
          "rawQuery": true,
          "rawSql": "SELECT (data->>'value')::float8 AS value\nFROM settings_num\nWHERE dbname = '$dbname'\n  AND tag_data->>'name' = 'fsync'\n  AND $__timeFilter(time)\nORDER BY time DESC LIMIT 1",
          "refId": "A"
        }
      ],
      "timeFrom": "6h",
      "title": "fsync",
      "type": "stat"
    },
    {
      "datasource": {
        "type": "grafana-postgresql-datasource",
        "uid": "pgwatch-metrics"
      },
      "description": "",
      "fieldConfig": {
        "defaults": {
          "color": {
            "mode": "thresholds"
          },
          "decimals": 0,
          "mappings": [
            {
              "options": {
                "0": {
                  "color": "dark-red",
                  "index": 0,
                  "text": "off"
                }
              },
              "type": "value"
            },
            {
              "options": {
                "1": {
                  "color": "dark-green",
                  "index": 1,
                  "text": "on"
                }
              },
              "type": "value"
            },
            {
              "options": {
                "match": "null",
                "result": {
                  "text": "N/A"
                }
              },
              "type": "special"
            }
          ],
          "thresholds": {
            "mode": "absolute",
            "steps": [
              {
                "color": "#d44a3a",
                "value": null
              },
              {
                "color": "#299c46",
                "value": 1
              }
            ]
          },
          "unit": "none"
        },
        "overrides": []
      },
      "gridPos": {
        "h": 4,
        "w": 4,
        "x": 4,
        "y": 6
      },
      "hideTimeOverride": true,
      "id": 10,
      "maxDataPoints": 100,
      "options": {
        "colorMode": "value",
        "graphMode": "none",
        "justifyMode": "auto",
        "orientation": "horizontal",
        "percentChangeColorMode": "standard",
        "reduceOptions": {
          "calcs": [
            "lastNotNull"
          ],
          "fields": "",
          "values": false
        },
        "showPercentChange": false,
        "textMode": "auto",
        "wideLayout": true
      },
      "pluginVersion": "12.3.1",
      "targets": [
        {
          "datasource": {
            "type": "grafana-postgresql-datasource",
            "uid": "pgwatch-metrics"
          },
          "format": "table",
          "metricColumn": "none",
          "rawQuery": true,
          "rawSql": "SELECT (data->>'value')::float8 AS value\nFROM settings_num\nWHERE dbname = '$dbname'\n  AND tag_data->>'name' = 'full_page_writes'\n  AND $__timeFilter(time)\nORDER BY time DESC LIMIT 1",
          "refId": "A"
        }
      ],
      "timeFrom": "6h",
      "title": "Full Page Writes",
      "type": "stat"
    },
    {
      "datasource": {
        "type": "grafana-postgresql-datasource",
        "uid": "pgwatch-metrics"
      },
      "description": "",
      "fieldConfig": {
        "defaults": {
          "color": {
            "mode": "thresholds"
          },
          "decimals": 0,
          "mappings": [
            {
              "options": {
                "0": {
                  "color": "dark-red",
                  "index": 0,
                  "text": "off"
                }
              },
              "type": "value"
            },
            {
              "options": {
                "1": {
                  "color": "dark-green",
                  "index": 1,
                  "text": "on"
                }
              },
              "type": "value"
            },
            {
              "options": {
                "match": "null",
                "result": {
                  "text": "N/A"
                }
              },
              "type": "special"
            }
          ],
          "thresholds": {
            "mode": "absolute",
            "steps": [
              {
                "color": "#d44a3a",
                "value": null
              },
              {
                "color": "#299c46",
                "value": 1
              }
            ]
          },
          "unit": "none"
        },
        "overrides": []
      },
      "gridPos": {
        "h": 4,
        "w": 4,
        "x": 8,
        "y": 6
      },
      "hideTimeOverride": true,
      "id": 11,
      "maxDataPoints": 100,
      "options": {
        "colorMode": "value",
        "graphMode": "none",
        "justifyMode": "auto",
        "orientation": "horizontal",
        "percentChangeColorMode": "standard",
        "reduceOptions": {
          "calcs": [
            "lastNotNull"
          ],
          "fields": "",
          "values": false
        },
        "showPercentChange": false,
        "textMode": "auto",
        "wideLayout": true
      },
      "pluginVersion": "12.3.1",
      "targets": [
        {
          "datasource": {
            "type": "grafana-postgresql-datasource",
            "uid": "pgwatch-metrics"
          },
          "format": "table",
          "metricColumn": "none",
          "rawQuery": true,
          "rawSql": "SELECT (data->>'value')::float8 AS value\nFROM settings_num\nWHERE dbname = '$dbname'\n  AND tag_data->>'name' = 'ssl'\n  AND $__timeFilter(time)\nORDER BY time DESC LIMIT 1",
          "refId": "A"
        }
      ],
      "timeFrom": "6h",
      "title": "SSL",
      "type": "stat"
    },
    {
      "datasource": {
        "type": "grafana-postgresql-datasource",
        "uid": "pgwatch-metrics"
      },
      "description": "",
      "fieldConfig": {
        "defaults": {
          "color": {
            "mode": "thresholds"
          },
          "decimals": 0,
          "mappings": [
            {
              "options": {
                "0": {
                  "color": "dark-red",
                  "index": 0,
                  "text": "off"
                }
              },
              "type": "value"
            },
            {
              "options": {
                "1": {
                  "color": "dark-green",
                  "index": 1,
                  "text": "on"
                }
              },
              "type": "value"
            },
            {
              "options": {
                "match": "null",
                "result": {
                  "text": "N/A"
                }
              },
              "type": "special"
            }
          ],
          "thresholds": {
            "mode": "absolute",
            "steps": [
              {
                "color": "#d44a3a",
                "value": null
              },
              {
                "color": "#299c46",
                "value": 1
              }
            ]
          },
          "unit": "none"
        },
        "overrides": []
      },
      "gridPos": {
        "h": 4,
        "w": 4,
        "x": 12,
        "y": 6
      },
      "hideTimeOverride": true,
      "id": 12,
      "maxDataPoints": 100,
      "options": {
        "colorMode": "value",
        "graphMode": "none",
        "justifyMode": "auto",
        "orientation": "horizontal",
        "percentChangeColorMode": "standard",
        "reduceOptions": {
          "calcs": [
            "lastNotNull"
          ],
          "fields": "",
          "values": false
        },
        "showPercentChange": false,
        "textMode": "auto",
        "wideLayout": true
      },
      "pluginVersion": "12.3.1",
      "targets": [
        {
          "datasource": {
            "type": "grafana-postgresql-datasource",
            "uid": "pgwatch-metrics"
          },
          "format": "table",
          "metricColumn": "none",
          "rawQuery": true,
          "rawSql": "SELECT (data->>'value')::float8 AS value\nFROM settings_num\nWHERE dbname = '$dbname'\n  AND tag_data->>'name' = 'data_checksums'\n  AND $__timeFilter(time)\nORDER BY time DESC LIMIT 1",
          "refId": "A"
        }
      ],
      "timeFrom": "6h",
      "title": "Data Checksums",
      "type": "stat"
    },
    {
      "datasource": {
        "type": "grafana-postgresql-datasource",
        "uid": "pgwatch-metrics"
      },
      "description": "",
      "fieldConfig": {
        "defaults": {
          "color": {
            "mode": "thresholds"
          },
          "decimals": 0,
          "mappings": [
            {
              "options": {
                "0": {
                  "color": "dark-red",
                  "index": 0,
                  "text": "off"
                }
              },
              "type": "value"
            },
            {
              "options": {
                "1": {
                  "color": "dark-green",
                  "index": 1,
                  "text": "on"
                }
              },
              "type": "value"
            },
            {
              "options": {
                "match": "null",
                "result": {
                  "text": "N/A"
                }
              },
              "type": "special"
            }
          ],
          "thresholds": {
            "mode": "absolute",
            "steps": [
              {
                "color": "#d44a3a",
                "value": null
              },
              {
                "color": "#299c46",
                "value": 1
              }
            ]
          },
          "unit": "none"
        },
        "overrides": []
      },
      "gridPos": {
        "h": 4,
        "w": 4,
        "x": 16,
        "y": 6
      },
      "hideTimeOverride": true,
      "id": 13,
      "maxDataPoints": 100,
      "options": {
        "colorMode": "value",
        "graphMode": "none",
        "justifyMode": "auto",
        "orientation": "horizontal",
        "percentChangeColorMode": "standard",
        "reduceOptions": {
          "calcs": [
            "lastNotNull"
          ],
          "fields": "",
          "values": false
        },
        "showPercentChange": false,
        "textMode": "auto",
        "wideLayout": true
      },
      "pluginVersion": "12.3.1",
      "targets": [
        {
          "datasource": {
            "type": "grafana-postgresql-datasource",
            "uid": "pgwatch-metrics"
          },
          "format": "table",
          "metricColumn": "none",
          "rawQuery": true,
          "rawSql": "SELECT (data->>'value')::float8 AS value\nFROM settings_num\nWHERE dbname = '$dbname'\n  AND tag_data->>'name' = 'wal_compression'\n  AND $__timeFilter(time)\nORDER BY time DESC LIMIT 1",
          "refId": "A"
        }
      ],
      "timeFrom": "6h",
      "title": "WAL Compression",
      "type": "stat"
    },
    {
      "datasource": {
        "type": "grafana-postgresql-datasource",
        "uid": "pgwatch-metrics"
      },
      "description": "",
      "fieldConfig": {
        "defaults": {
          "color": {
            "mode": "thresholds"
          },
          "decimals": 0,
          "mappings": [
            {
              "options": {
                "0": {
                  "color": "dark-red",
                  "index": 0,
                  "text": "off"
                }
              },
              "type": "value"
            },
            {
              "options": {
                "1": {
                  "color": "dark-green",
                  "index": 1,
                  "text": "on"
                }
              },
              "type": "value"
            },
            {
              "options": {
                "match": "null",
                "result": {
                  "text": "N/A"
                }
              },
              "type": "special"
            }
          ],
          "thresholds": {
            "mode": "absolute",
            "steps": [
              {
                "color": "#d44a3a",
                "value": null
              },
              {
                "color": "#299c46",
                "value": 1
              }
            ]
          },
          "unit": "none"
        },
        "overrides": []
      },
      "gridPos": {
        "h": 4,
        "w": 4,
        "x": 20,
        "y": 6
      },
      "hideTimeOverride": true,
      "id": 14,
      "maxDataPoints": 100,
      "options": {
        "colorMode": "value",
        "graphMode": "none",
        "justifyMode": "auto",
        "orientation": "horizontal",
        "percentChangeColorMode": "standard",
        "reduceOptions": {
          "calcs": [
            "lastNotNull"
          ],
          "fields": "",
          "values": false
        },
        "showPercentChange": false,
        "textMode": "auto",
        "wideLayout": true
      },
      "pluginVersion": "12.3.1",
      "targets": [
        {
          "datasource": {
            "type": "grafana-postgresql-datasource",
            "uid": "pgwatch-metrics"
          },
          "format": "table",
          "metricColumn": "none",
          "rawQuery": true,
          "rawSql": "SELECT (data->>'value')::float8 AS value\nFROM settings_num\nWHERE dbname = '$dbname'\n  AND tag_data->>'name' = 'wal_log_hints'\n  AND $__timeFilter(time)\nORDER BY time DESC LIMIT 1",
          "refId": "A"
        }
      ],
      "timeFrom": "6h",
      "title": "WAL Log Hints",
      "type": "stat"
    },
    {
      "collapsed": false,
      "gridPos": {
        "h": 1,
        "w": 24,
        "x": 0,
        "y": 10
      },
      "id": 15,
      "panels": [],
      "title": "Autovacuum",
      "type": "row"
    },
    {
      "datasource": {
        "type": "grafana-postgresql-datasource",
        "uid": "pgwatch-metrics"
      },
      "description": "",
      "fieldConfig": {
        "defaults": {
          "color": {
            "mode": "thresholds"
          },
          "decimals": 0,
          "mappings": [
            {
              "options": {
                "0": {
                  "color": "dark-red",
                  "index": 0,
                  "text": "off"
                }
              },
              "type": "value"
            },
            {
              "options": {
                "1": {
                  "color": "dark-green",
                  "index": 1,
                  "text": "on"
                }
              },
              "type": "value"
            },
            {
              "options": {
                "match": "null",
                "result": {
                  "text": "N/A"
                }
              },
              "type": "special"
            }
          ],
          "thresholds": {
            "mode": "absolute",
            "steps": [
              {
                "color": "#d44a3a",
                "value": null
              },
              {
                "color": "#299c46",
                "value": 1
              }
            ]
          },
          "unit": "none"
        },
        "overrides": []
      },
      "gridPos": {
        "h": 4,
        "w": 4,
        "x": 0,
        "y": 11
      },
      "hideTimeOverride": true,
      "id": 16,
      "maxDataPoints": 100,
      "options": {
        "colorMode": "value",
        "graphMode": "none",
        "justifyMode": "auto",
        "orientation": "horizontal",
        "percentChangeColorMode": "standard",
        "reduceOptions": {
          "calcs": [
            "lastNotNull"
          ],
          "fields": "",
          "values": false
        },
        "showPercentChange": false,
        "textMode": "auto",
        "wideLayout": true
      },
      "pluginVersion": "12.3.1",
      "targets": [
        {
          "datasource": {
            "type": "grafana-postgresql-datasource",
            "uid": "pgwatch-metrics"
          },
          "format": "table",
          "metricColumn": "none",
          "rawQuery": true,
          "rawSql": "SELECT (data->>'value')::float8 AS value\nFROM settings_num\nWHERE dbname = '$dbname'\n  AND tag_data->>'name' = 'autovacuum'\n  AND $__timeFilter(time)\nORDER BY time DESC LIMIT 1",
          "refId": "A"
        }
      ],
      "timeFrom": "6h",
      "title": "Autovacuum",
      "type": "stat"
    },
    {
      "datasource": {
        "type": "grafana-postgresql-datasource",
        "uid": "pgwatch-metrics"
      },
      "description": "",
      "fieldConfig": {
        "defaults": {
          "color": {
            "mode": "thresholds"
          },
          "decimals": 0,
          "mappings": [
            {
              "options": {
                "match": "null",
                "result": {
                  "text": "N/A"
                }
              },
              "type": "special"
            }
          ],
          "thresholds": {
            "mode": "absolute",
            "steps": [
              {
                "color": "blue"
              }
            ]
          },
          "unit": "none"
        },
        "overrides": []
      },
      "gridPos": {
        "h": 4,
        "w": 4,
        "x": 4,
        "y": 11
      },
      "hideTimeOverride": true,
      "id": 17,
      "maxDataPoints": 100,
      "options": {
        "colorMode": "value",
        "graphMode": "none",
        "justifyMode": "auto",
        "orientation": "horizontal",
        "percentChangeColorMode": "standard",
        "reduceOptions": {
          "calcs": [
            "lastNotNull"
          ],
          "fields": "",
          "values": false
        },
        "showPercentChange": false,
        "textMode": "auto",
        "wideLayout": true
      },
      "pluginVersion": "12.3.1",
      "targets": [
        {
          "datasource": {
            "type": "grafana-postgresql-datasource",
            "uid": "pgwatch-metrics"
          },
          "format": "table",
          "metricColumn": "none",
          "rawQuery": true,
          "rawSql": "SELECT (data->>'value')::float8 AS value\nFROM settings_num\nWHERE dbname = '$dbname'\n  AND tag_data->>'name' = 'autovacuum_max_workers'\n  AND $__timeFilter(time)\nORDER BY time DESC LIMIT 1",
          "refId": "A"
        }
      ],
      "timeFrom": "6h",
      "title": "AV Max Workers",
      "type": "stat"
    },
    {
      "datasource": {
        "type": "grafana-postgresql-datasource",
        "uid": "pgwatch-metrics"
      },
      "description": "",
      "fieldConfig": {
        "defaults": {
          "color": {
            "mode": "thresholds"
          },
          "decimals": 3,
          "mappings": [
            {
              "options": {
                "match": "null",
                "result": {
                  "text": "N/A"
                }
              },
              "type": "special"
            }
          ],
          "thresholds": {
            "mode": "absolute",
            "steps": [
              {
                "color": "blue"
              }
            ]
          },
          "unit": "percentunit"
        },
        "overrides": []
      },
      "gridPos": {
        "h": 4,
        "w": 4,
        "x": 8,
        "y": 11
      },
      "hideTimeOverride": true,
      "id": 18,
      "maxDataPoints": 100,
      "options": {
        "colorMode": "value",
        "graphMode": "none",
        "justifyMode": "auto",
        "orientation": "horizontal",
        "percentChangeColorMode": "standard",
        "reduceOptions": {
          "calcs": [
            "lastNotNull"
          ],
          "fields": "",
          "values": false
        },
        "showPercentChange": false,
        "textMode": "auto",
        "wideLayout": true
      },
      "pluginVersion": "12.3.1",
      "targets": [
        {
          "datasource": {
            "type": "grafana-postgresql-datasource",
            "uid": "pgwatch-metrics"
          },
          "format": "table",
          "metricColumn": "none",
          "rawQuery": true,
          "rawSql": "SELECT (data->>'value')::float8 AS value\nFROM settings_num\nWHERE dbname = '$dbname'\n  AND tag_data->>'name' = 'autovacuum_vacuum_scale_factor'\n  AND $__timeFilter(time)\nORDER BY time DESC LIMIT 1",
          "refId": "A"
        }
      ],
      "timeFrom": "6h",
      "title": "AV Vacuum Scale Factor",
      "type": "stat"
    },
    {
      "datasource": {
        "type": "grafana-postgresql-datasource",
        "uid": "pgwatch-metrics"
      },
      "description": "",
      "fieldConfig": {
        "defaults": {
          "color": {
            "mode": "thresholds"
          },
          "decimals": 0,
          "mappings": [
            {
              "options": {
                "match": "null",
                "result": {
                  "text": "N/A"
                }
              },
              "type": "special"
            }
          ],
          "thresholds": {
            "mode": "absolute",
            "steps": [
              {
                "color": "blue"
              }
            ]
          },
          "unit": "none"
        },
        "overrides": []
      },
      "gridPos": {
        "h": 4,
        "w": 4,
        "x": 12,
        "y": 11
      },
      "hideTimeOverride": true,
      "id": 19,
      "maxDataPoints": 100,
      "options": {
        "colorMode": "value",
        "graphMode": "none",
        "justifyMode": "auto",
        "orientation": "horizontal",
        "percentChangeColorMode": "standard",
        "reduceOptions": {
          "calcs": [
            "lastNotNull"
          ],
          "fields": "",
          "values": false
        },
        "showPercentChange": false,
        "textMode": "auto",
        "wideLayout": true
      },
      "pluginVersion": "12.3.1",
      "targets": [
        {
          "datasource": {
            "type": "grafana-postgresql-datasource",
            "uid": "pgwatch-metrics"
          },
          "format": "table",
          "metricColumn": "none",
          "rawQuery": true,
          "rawSql": "SELECT (data->>'value')::float8 AS value\nFROM settings_num\nWHERE dbname = '$dbname'\n  AND tag_data->>'name' = 'autovacuum_vacuum_threshold'\n  AND $__timeFilter(time)\nORDER BY time DESC LIMIT 1",
          "refId": "A"
        }
      ],
      "timeFrom": "6h",
      "title": "AV Vacuum Threshold",
      "type": "stat"
    },
    {
      "datasource": {
        "type": "grafana-postgresql-datasource",
        "uid": "pgwatch-metrics"
      },
      "description": "",
      "fieldConfig": {
        "defaults": {
          "color": {
            "mode": "thresholds"
          },
          "decimals": 3,
          "mappings": [
            {
              "options": {
                "match": "null",
                "result": {
                  "text": "N/A"
                }
              },
              "type": "special"
            }
          ],
          "thresholds": {
            "mode": "absolute",
            "steps": [
              {
                "color": "blue"
              }
            ]
          },
          "unit": "percentunit"
        },
        "overrides": []
      },
      "gridPos": {
        "h": 4,
        "w": 4,
        "x": 16,
        "y": 11
      },
      "hideTimeOverride": true,
      "id": 20,
      "maxDataPoints": 100,
      "options": {
        "colorMode": "value",
        "graphMode": "none",
        "justifyMode": "auto",
        "orientation": "horizontal",
        "percentChangeColorMode": "standard",
        "reduceOptions": {
          "calcs": [
            "lastNotNull"
          ],
          "fields": "",
          "values": false
        },
        "showPercentChange": false,
        "textMode": "auto",
        "wideLayout": true
      },
      "pluginVersion": "12.3.1",
      "targets": [
        {
          "datasource": {
            "type": "grafana-postgresql-datasource",
            "uid": "pgwatch-metrics"
          },
          "format": "table",
          "metricColumn": "none",
          "rawQuery": true,
          "rawSql": "SELECT (data->>'value')::float8 AS value\nFROM settings_num\nWHERE dbname = '$dbname'\n  AND tag_data->>'name' = 'autovacuum_analyze_scale_factor'\n  AND $__timeFilter(time)\nORDER BY time DESC LIMIT 1",
          "refId": "A"
        }
      ],
      "timeFrom": "6h",
      "title": "AV Analyze Scale Factor",
      "type": "stat"
    },
    {
      "datasource": {
        "type": "grafana-postgresql-datasource",
        "uid": "pgwatch-metrics"
      },
      "description": "",
      "fieldConfig": {
        "defaults": {
          "color": {
            "mode": "thresholds"
          },
          "decimals": 0,
          "mappings": [
            {
              "options": {
                "match": "null",
                "result": {
                  "text": "N/A"
                }
              },
              "type": "special"
            }
          ],
          "thresholds": {
            "mode": "absolute",
            "steps": [
              {
                "color": "blue"
              }
            ]
          },
          "unit": "none"
        },
        "overrides": []
      },
      "gridPos": {
        "h": 4,
        "w": 4,
        "x": 20,
        "y": 11
      },
      "hideTimeOverride": true,
      "id": 21,
      "maxDataPoints": 100,
      "options": {
        "colorMode": "value",
        "graphMode": "none",
        "justifyMode": "auto",
        "orientation": "horizontal",
        "percentChangeColorMode": "standard",
        "reduceOptions": {
          "calcs": [
            "lastNotNull"
          ],
          "fields": "",
          "values": false
        },
        "showPercentChange": false,
        "textMode": "auto",
        "wideLayout": true
      },
      "pluginVersion": "12.3.1",
      "targets": [
        {
          "datasource": {
            "type": "grafana-postgresql-datasource",
            "uid": "pgwatch-metrics"
          },
          "format": "table",
          "metricColumn": "none",
          "rawQuery": true,
          "rawSql": "SELECT (data->>'value')::float8 AS value\nFROM settings_num\nWHERE dbname = '$dbname'\n  AND tag_data->>'name' = 'autovacuum_analyze_threshold'\n  AND $__timeFilter(time)\nORDER BY time DESC LIMIT 1",
          "refId": "A"
        }
      ],
      "timeFrom": "6h",
      "title": "AV Analyze Threshold",
      "type": "stat"
    },
    {
      "collapsed": false,
      "gridPos": {
        "h": 1,
        "w": 24,
        "x": 0,
        "y": 15
      },
      "id": 22,
      "panels": [],
      "title": "Parallelism & Replication",
      "type": "row"
    },
    {
      "datasource": {
        "type": "grafana-postgresql-datasource",
        "uid": "pgwatch-metrics"
      },
      "description": "",
      "fieldConfig": {
        "defaults": {
          "color": {
            "mode": "thresholds"
          },
          "decimals": 0,
          "mappings": [
            {
              "options": {
                "match": "null",
                "result": {
                  "text": "N/A"
                }
              },
              "type": "special"
            }
          ],
          "thresholds": {
            "mode": "absolute",
            "steps": [
              {
                "color": "blue"
              }
            ]
          },
          "unit": "none"
        },
        "overrides": []
      },
      "gridPos": {
        "h": 4,
        "w": 4,
        "x": 0,
        "y": 16
      },
      "hideTimeOverride": true,
      "id": 23,
      "maxDataPoints": 100,
      "options": {
        "colorMode": "value",
        "graphMode": "none",
        "justifyMode": "auto",
        "orientation": "horizontal",
        "percentChangeColorMode": "standard",
        "reduceOptions": {
          "calcs": [
            "lastNotNull"
          ],
          "fields": "",
          "values": false
        },
        "showPercentChange": false,
        "textMode": "auto",
        "wideLayout": true
      },
      "pluginVersion": "12.3.1",
      "targets": [
        {
          "datasource": {
            "type": "grafana-postgresql-datasource",
            "uid": "pgwatch-metrics"
          },
          "format": "table",
          "metricColumn": "none",
          "rawQuery": true,
          "rawSql": "SELECT (data->>'value')::float8 AS value\nFROM settings_num\nWHERE dbname = '$dbname'\n  AND tag_data->>'name' = 'max_worker_processes'\n  AND $__timeFilter(time)\nORDER BY time DESC LIMIT 1",
          "refId": "A"
        }
      ],
      "timeFrom": "6h",
      "title": "Max Worker Processes",
      "type": "stat"
    },
    {
      "datasource": {
        "type": "grafana-postgresql-datasource",
        "uid": "pgwatch-metrics"
      },
      "description": "",
      "fieldConfig": {
        "defaults": {
          "color": {
            "mode": "thresholds"
          },
          "decimals": 0,
          "mappings": [
            {
              "options": {
                "match": "null",
                "result": {
                  "text": "N/A"
                }
              },
              "type": "special"
            }
          ],
          "thresholds": {
            "mode": "absolute",
            "steps": [
              {
                "color": "blue"
              }
            ]
          },
          "unit": "none"
        },
        "overrides": []
      },
      "gridPos": {
        "h": 4,
        "w": 4,
        "x": 4,
        "y": 16
      },
      "hideTimeOverride": true,
      "id": 24,
      "maxDataPoints": 100,
      "options": {
        "colorMode": "value",
        "graphMode": "none",
        "justifyMode": "auto",
        "orientation": "horizontal",
        "percentChangeColorMode": "standard",
        "reduceOptions": {
          "calcs": [
            "lastNotNull"
          ],
          "fields": "",
          "values": false
        },
        "showPercentChange": false,
        "textMode": "auto",
        "wideLayout": true
      },
      "pluginVersion": "12.3.1",
      "targets": [
        {
          "datasource": {
            "type": "grafana-postgresql-datasource",
            "uid": "pgwatch-metrics"
          },
          "format": "table",
          "metricColumn": "none",
          "rawQuery": true,
          "rawSql": "SELECT (data->>'value')::float8 AS value\nFROM settings_num\nWHERE dbname = '$dbname'\n  AND tag_data->>'name' = 'max_parallel_workers'\n  AND $__timeFilter(time)\nORDER BY time DESC LIMIT 1",
          "refId": "A"
        }
      ],
      "timeFrom": "6h",
      "title": "Max Parallel Workers",
      "type": "stat"
    },
    {
      "datasource": {
        "type": "grafana-postgresql-datasource",
        "uid": "pgwatch-metrics"
      },
      "description": "",
      "fieldConfig": {
        "defaults": {
          "color": {
            "mode": "thresholds"
          },
          "decimals": 0,
          "mappings": [
            {
              "options": {
                "match": "null",
                "result": {
                  "text": "N/A"
                }
              },
              "type": "special"
            }
          ],
          "thresholds": {
            "mode": "absolute",
            "steps": [
              {
                "color": "blue"
              }
            ]
          },
          "unit": "none"
        },
        "overrides": []
      },
      "gridPos": {
        "h": 4,
        "w": 4,
        "x": 8,
        "y": 16
      },
      "hideTimeOverride": true,
      "id": 25,
      "maxDataPoints": 100,
      "options": {
        "colorMode": "value",
        "graphMode": "none",
        "justifyMode": "auto",
        "orientation": "horizontal",
        "percentChangeColorMode": "standard",
        "reduceOptions": {
          "calcs": [
            "lastNotNull"
          ],
          "fields": "",
          "values": false
        },
        "showPercentChange": false,
        "textMode": "auto",
        "wideLayout": true
      },
      "pluginVersion": "12.3.1",
      "targets": [
        {
          "datasource": {
            "type": "grafana-postgresql-datasource",
            "uid": "pgwatch-metrics"
          },
          "format": "table",
          "metricColumn": "none",
          "rawQuery": true,
          "rawSql": "SELECT (data->>'value')::float8 AS value\nFROM settings_num\nWHERE dbname = '$dbname'\n  AND tag_data->>'name' = 'max_parallel_workers_per_gather'\n  AND $__timeFilter(time)\nORDER BY time DESC LIMIT 1",
          "refId": "A"
        }
      ],
      "timeFrom": "6h",
      "title": "Max Parallel Workers / Gather",
      "type": "stat"
    },
    {
      "datasource": {
        "type": "grafana-postgresql-datasource",
        "uid": "pgwatch-metrics"
      },
      "description": "",
      "fieldConfig": {
        "defaults": {
          "color": {
            "mode": "thresholds"
          },
          "decimals": 0,
          "mappings": [
            {
              "options": {
                "match": "null",
                "result": {
                  "text": "N/A"
                }
              },
              "type": "special"
            }
          ],
          "thresholds": {
            "mode": "absolute",
            "steps": [
              {
                "color": "blue"
              }
            ]
          },
          "unit": "none"
        },
        "overrides": []
      },
      "gridPos": {
        "h": 4,
        "w": 4,
        "x": 12,
        "y": 16
      },
      "hideTimeOverride": true,
      "id": 26,
      "maxDataPoints": 100,
      "options": {
        "colorMode": "value",
        "graphMode": "none",
        "justifyMode": "auto",
        "orientation": "horizontal",
        "percentChangeColorMode": "standard",
        "reduceOptions": {
          "calcs": [
            "lastNotNull"
          ],
          "fields": "",
          "values": false
        },
        "showPercentChange": false,
        "textMode": "auto",
        "wideLayout": true
      },
      "pluginVersion": "12.3.1",
      "targets": [
        {
          "datasource": {
            "type": "grafana-postgresql-datasource",
            "uid": "pgwatch-metrics"
          },
          "format": "table",
          "metricColumn": "none",
          "rawQuery": true,
          "rawSql": "SELECT (data->>'value')::float8 AS value\nFROM settings_num\nWHERE dbname = '$dbname'\n  AND tag_data->>'name' = 'max_wal_senders'\n  AND $__timeFilter(time)\nORDER BY time DESC LIMIT 1",
          "refId": "A"
        }
      ],
      "timeFrom": "6h",
      "title": "Max WAL Senders",
      "type": "stat"
    },
    {
      "datasource": {
        "type": "grafana-postgresql-datasource",
        "uid": "pgwatch-metrics"
      },
      "description": "",
      "fieldConfig": {
        "defaults": {
          "color": {
            "mode": "thresholds"
          },
          "decimals": 0,
          "mappings": [
            {
              "options": {
                "match": "null",
                "result": {
                  "text": "N/A"
                }
              },
              "type": "special"
            }
          ],
          "thresholds": {
            "mode": "absolute",
            "steps": [
              {
                "color": "blue"
              }
            ]
          },
          "unit": "none"
        },
        "overrides": []
      },
      "gridPos": {
        "h": 4,
        "w": 4,
        "x": 16,
        "y": 16
      },
      "hideTimeOverride": true,
      "id": 27,
      "maxDataPoints": 100,
      "options": {
        "colorMode": "value",
        "graphMode": "none",
        "justifyMode": "auto",
        "orientation": "horizontal",
        "percentChangeColorMode": "standard",
        "reduceOptions": {
          "calcs": [
            "lastNotNull"
          ],
          "fields": "",
          "values": false
        },
        "showPercentChange": false,
        "textMode": "auto",
        "wideLayout": true
      },
      "pluginVersion": "12.3.1",
      "targets": [
        {
          "datasource": {
            "type": "grafana-postgresql-datasource",
            "uid": "pgwatch-metrics"
          },
          "format": "table",
          "metricColumn": "none",
          "rawQuery": true,
          "rawSql": "SELECT (data->>'value')::float8 AS value\nFROM settings_num\nWHERE dbname = '$dbname'\n  AND tag_data->>'name' = 'max_replication_slots'\n  AND $__timeFilter(time)\nORDER BY time DESC LIMIT 1",
          "refId": "A"
        }
      ],
      "timeFrom": "6h",
      "title": "Max Replication Slots",
      "type": "stat"
    },
    {
      "datasource": {
        "type": "grafana-postgresql-datasource",
        "uid": "pgwatch-metrics"
      },
      "description": "",
      "fieldConfig": {
        "defaults": {
          "color": {
            "mode": "thresholds"
          },
          "decimals": 0,
          "mappings": [
            {
              "options": {
                "0": {
                  "color": "dark-red",
                  "index": 0,
                  "text": "off"
                }
              },
              "type": "value"
            },
            {
              "options": {
                "1": {
                  "color": "dark-green",
                  "index": 1,
                  "text": "on"
                }
              },
              "type": "value"
            },
            {
              "options": {
                "match": "null",
                "result": {
                  "text": "N/A"
                }
              },
              "type": "special"
            }
          ],
          "thresholds": {
            "mode": "absolute",
            "steps": [
              {
                "color": "#d44a3a",
                "value": null
              },
              {
                "color": "#299c46",
                "value": 1
              }
            ]
          },
          "unit": "none"
        },
        "overrides": []
      },
      "gridPos": {
        "h": 4,
        "w": 4,
        "x": 20,
        "y": 16
      },
      "hideTimeOverride": true,
      "id": 28,
      "maxDataPoints": 100,
      "options": {
        "colorMode": "value",
        "graphMode": "none",
        "justifyMode": "auto",
        "orientation": "horizontal",
        "percentChangeColorMode": "standard",
        "reduceOptions": {
          "calcs": [
            "lastNotNull"
          ],
          "fields": "",
          "values": false
        },
        "showPercentChange": false,
        "textMode": "auto",
        "wideLayout": true
      },
      "pluginVersion": "12.3.1",
      "targets": [
        {
          "datasource": {
            "type": "grafana-postgresql-datasource",
            "uid": "pgwatch-metrics"
          },
          "format": "table",
          "metricColumn": "none",
          "rawQuery": true,
          "rawSql": "SELECT (data->>'value')::float8 AS value\nFROM settings_num\nWHERE dbname = '$dbname'\n  AND tag_data->>'name' = 'hot_standby'\n  AND $__timeFilter(time)\nORDER BY time DESC LIMIT 1",
          "refId": "A"
        }
      ],
      "timeFrom": "6h",
      "title": "Hot Standby",
      "type": "stat"
    },
    {
      "collapsed": false,
      "gridPos": {
        "h": 1,
        "w": 24,
        "x": 0,
        "y": 20
      },
      "id": 29,
      "panels": [],
      "title": "WAL & Checkpoints",
      "type": "row"
    },
    {
      "datasource": {
        "type": "grafana-postgresql-datasource",
        "uid": "pgwatch-metrics"
      },
      "description": "1=minimal  2=replica  3=logical",
      "fieldConfig": {
        "defaults": {
          "color": {
            "mode": "thresholds"
          },
          "decimals": 0,
          "mappings": [
            {
              "options": {
                "1": {
                  "index": 0,
                  "text": "minimal"
                },
                "2": {
                  "index": 1,
                  "text": "replica"
                },
                "3": {
                  "index": 2,
                  "text": "logical"
                }
              },
              "type": "value"
            },
            {
              "options": {
                "match": "null",
                "result": {
                  "text": "N/A"
                }
              },
              "type": "special"
            }
          ],
          "thresholds": {
            "mode": "absolute",
            "steps": [
              {
                "color": "blue"
              }
            ]
          },
          "unit": "none"
        },
        "overrides": []
      },
      "gridPos": {
        "h": 4,
        "w": 4,
        "x": 0,
        "y": 21
      },
      "hideTimeOverride": true,
      "id": 30,
      "maxDataPoints": 100,
      "options": {
        "colorMode": "value",
        "graphMode": "none",
        "justifyMode": "auto",
        "orientation": "horizontal",
        "percentChangeColorMode": "standard",
        "reduceOptions": {
          "calcs": [
            "lastNotNull"
          ],
          "fields": "",
          "values": false
        },
        "showPercentChange": false,
        "textMode": "auto",
        "wideLayout": true
      },
      "pluginVersion": "12.3.1",
      "targets": [
        {
          "datasource": {
            "type": "grafana-postgresql-datasource",
            "uid": "pgwatch-metrics"
          },
          "format": "table",
          "metricColumn": "none",
          "rawQuery": true,
          "rawSql": "SELECT (data->>'value')::float8 AS value\nFROM settings_num\nWHERE dbname = '$dbname'\n  AND tag_data->>'name' = 'wal_level'\n  AND $__timeFilter(time)\nORDER BY time DESC LIMIT 1",
          "refId": "A"
        }
      ],
      "timeFrom": "6h",
      "title": "WAL Level",
      "type": "stat"
    },
    {
      "datasource": {
        "type": "grafana-postgresql-datasource",
        "uid": "pgwatch-metrics"
      },
      "description": "1=off  2=on  3=always",
      "fieldConfig": {
        "defaults": {
          "color": {
            "mode": "thresholds"
          },
          "decimals": 0,
          "mappings": [
            {
              "options": {
                "1": {
                  "index": 0,
                  "text": "off"
                },
                "2": {
                  "index": 1,
                  "text": "on"
                },
                "3": {
                  "index": 2,
                  "text": "always"
                }
              },
              "type": "value"
            },
            {
              "options": {
                "match": "null",
                "result": {
                  "text": "N/A"
                }
              },
              "type": "special"
            }
          ],
          "thresholds": {
            "mode": "absolute",
            "steps": [
              {
                "color": "blue"
              }
            ]
          },
          "unit": "none"
        },
        "overrides": []
      },
      "gridPos": {
        "h": 4,
        "w": 4,
        "x": 4,
        "y": 21
      },
      "hideTimeOverride": true,
      "id": 31,
      "maxDataPoints": 100,
      "options": {
        "colorMode": "value",
        "graphMode": "none",
        "justifyMode": "auto",
        "orientation": "horizontal",
        "percentChangeColorMode": "standard",
        "reduceOptions": {
          "calcs": [
            "lastNotNull"
          ],
          "fields": "",
          "values": false
        },
        "showPercentChange": false,
        "textMode": "auto",
        "wideLayout": true
      },
      "pluginVersion": "12.3.1",
      "targets": [
        {
          "datasource": {
            "type": "grafana-postgresql-datasource",
            "uid": "pgwatch-metrics"
          },
          "format": "table",
          "metricColumn": "none",
          "rawQuery": true,
          "rawSql": "SELECT (data->>'value')::float8 AS value\nFROM settings_num\nWHERE dbname = '$dbname'\n  AND tag_data->>'name' = 'archive_mode'\n  AND $__timeFilter(time)\nORDER BY time DESC LIMIT 1",
          "refId": "A"
        }
      ],
      "timeFrom": "6h",
      "title": "Archive Mode",
      "type": "stat"
    },
    {
      "datasource": {
        "type": "grafana-postgresql-datasource",
        "uid": "pgwatch-metrics"
      },
      "description": "",
      "fieldConfig": {
        "defaults": {
          "color": {
            "mode": "thresholds"
          },
          "decimals": 0,
          "mappings": [
            {
              "options": {
                "match": "null",
                "result": {
                  "text": "N/A"
                }
              },
              "type": "special"
            }
          ],
          "thresholds": {
            "mode": "absolute",
            "steps": [
              {
                "color": "blue"
              }
            ]
          },
          "unit": "s"
        },
        "overrides": []
      },
      "gridPos": {
        "h": 4,
        "w": 4,
        "x": 8,
        "y": 21
      },
      "hideTimeOverride": true,
      "id": 32,
      "maxDataPoints": 100,
      "options": {
        "colorMode": "value",
        "graphMode": "none",
        "justifyMode": "auto",
        "orientation": "horizontal",
        "percentChangeColorMode": "standard",
        "reduceOptions": {
          "calcs": [
            "lastNotNull"
          ],
          "fields": "",
          "values": false
        },
        "showPercentChange": false,
        "textMode": "auto",
        "wideLayout": true
      },
      "pluginVersion": "12.3.1",
      "targets": [
        {
          "datasource": {
            "type": "grafana-postgresql-datasource",
            "uid": "pgwatch-metrics"
          },
          "format": "table",
          "metricColumn": "none",
          "rawQuery": true,
          "rawSql": "SELECT (data->>'value')::float8 AS value\nFROM settings_num\nWHERE dbname = '$dbname'\n  AND tag_data->>'name' = 'checkpoint_timeout'\n  AND $__timeFilter(time)\nORDER BY time DESC LIMIT 1",
          "refId": "A"
        }
      ],
      "timeFrom": "6h",
      "title": "Checkpoint Timeout",
      "type": "stat"
    },
    {
      "datasource": {
        "type": "grafana-postgresql-datasource",
        "uid": "pgwatch-metrics"
      },
      "description": "",
      "fieldConfig": {
        "defaults": {
          "color": {
            "mode": "thresholds"
          },
          "decimals": 2,
          "mappings": [
            {
              "options": {
                "match": "null",
                "result": {
                  "text": "N/A"
                }
              },
              "type": "special"
            }
          ],
          "thresholds": {
            "mode": "absolute",
            "steps": [
              {
                "color": "blue"
              }
            ]
          },
          "unit": "percentunit"
        },
        "overrides": []
      },
      "gridPos": {
        "h": 4,
        "w": 4,
        "x": 12,
        "y": 21
      },
      "hideTimeOverride": true,
      "id": 33,
      "maxDataPoints": 100,
      "options": {
        "colorMode": "value",
        "graphMode": "none",
        "justifyMode": "auto",
        "orientation": "horizontal",
        "percentChangeColorMode": "standard",
        "reduceOptions": {
          "calcs": [
            "lastNotNull"
          ],
          "fields": "",
          "values": false
        },
        "showPercentChange": false,
        "textMode": "auto",
        "wideLayout": true
      },
      "pluginVersion": "12.3.1",
      "targets": [
        {
          "datasource": {
            "type": "grafana-postgresql-datasource",
            "uid": "pgwatch-metrics"
          },
          "format": "table",
          "metricColumn": "none",
          "rawQuery": true,
          "rawSql": "SELECT (data->>'value')::float8 AS value\nFROM settings_num\nWHERE dbname = '$dbname'\n  AND tag_data->>'name' = 'checkpoint_completion_target'\n  AND $__timeFilter(time)\nORDER BY time DESC LIMIT 1",
          "refId": "A"
        }
      ],
      "timeFrom": "6h",
      "title": "Checkpoint Completion Target",
      "type": "stat"
    },
    {
      "datasource": {
        "type": "grafana-postgresql-datasource",
        "uid": "pgwatch-metrics"
      },
      "description": "In MB",
      "fieldConfig": {
        "defaults": {
          "color": {
            "mode": "thresholds"
          },
          "decimals": 0,
          "mappings": [
            {
              "options": {
                "match": "null",
                "result": {
                  "text": "N/A"
                }
              },
              "type": "special"
            }
          ],
          "thresholds": {
            "mode": "absolute",
            "steps": [
              {
                "color": "blue"
              }
            ]
          },
          "unit": "short"
        },
        "overrides": []
      },
      "gridPos": {
        "h": 4,
        "w": 4,
        "x": 16,
        "y": 21
      },
      "hideTimeOverride": true,
      "id": 34,
      "maxDataPoints": 100,
      "options": {
        "colorMode": "value",
        "graphMode": "none",
        "justifyMode": "auto",
        "orientation": "horizontal",
        "percentChangeColorMode": "standard",
        "reduceOptions": {
          "calcs": [
            "lastNotNull"
          ],
          "fields": "",
          "values": false
        },
        "showPercentChange": false,
        "textMode": "auto",
        "wideLayout": true
      },
      "pluginVersion": "12.3.1",
      "targets": [
        {
          "datasource": {
            "type": "grafana-postgresql-datasource",
            "uid": "pgwatch-metrics"
          },
          "format": "table",
          "metricColumn": "none",
          "rawQuery": true,
          "rawSql": "SELECT (data->>'value')::float8 AS value\nFROM settings_num\nWHERE dbname = '$dbname'\n  AND tag_data->>'name' = 'min_wal_size'\n  AND $__timeFilter(time)\nORDER BY time DESC LIMIT 1",
          "refId": "A"
        }
      ],
      "timeFrom": "6h",
      "title": "Min WAL Size",
      "type": "stat"
    },
    {
      "datasource": {
        "type": "grafana-postgresql-datasource",
        "uid": "pgwatch-metrics"
      },
      "description": "In MB",
      "fieldConfig": {
        "defaults": {
          "color": {
            "mode": "thresholds"
          },
          "decimals": 0,
          "mappings": [
            {
              "options": {
                "match": "null",
                "result": {
                  "text": "N/A"
                }
              },
              "type": "special"
            }
          ],
          "thresholds": {
            "mode": "absolute",
            "steps": [
              {
                "color": "blue"
              }
            ]
          },
          "unit": "short"
        },
        "overrides": []
      },
      "gridPos": {
        "h": 4,
        "w": 4,
        "x": 20,
        "y": 21
      },
      "hideTimeOverride": true,
      "id": 35,
      "maxDataPoints": 100,
      "options": {
        "colorMode": "value",
        "graphMode": "none",
        "justifyMode": "auto",
        "orientation": "horizontal",
        "percentChangeColorMode": "standard",
        "reduceOptions": {
          "calcs": [
            "lastNotNull"
          ],
          "fields": "",
          "values": false
        },
        "showPercentChange": false,
        "textMode": "auto",
        "wideLayout": true
      },
      "pluginVersion": "12.3.1",
      "targets": [
        {
          "datasource": {
            "type": "grafana-postgresql-datasource",
            "uid": "pgwatch-metrics"
          },
          "format": "table",
          "metricColumn": "none",
          "rawQuery": true,
          "rawSql": "SELECT (data->>'value')::float8 AS value\nFROM settings_num\nWHERE dbname = '$dbname'\n  AND tag_data->>'name' = 'max_wal_size'\n  AND $__timeFilter(time)\nORDER BY time DESC LIMIT 1",
          "refId": "A"
        }
      ],
      "timeFrom": "6h",
      "title": "Max WAL Size",
      "type": "stat"
    },
    {
      "collapsed": false,
      "gridPos": {
        "h": 1,
        "w": 24,
        "x": 0,
        "y": 25
      },
      "id": 36,
      "panels": [],
      "title": "Timeouts & Locks",
      "type": "row"
    },
    {
      "datasource": {
        "type": "grafana-postgresql-datasource",
        "uid": "pgwatch-metrics"
      },
      "description": "",
      "fieldConfig": {
        "defaults": {
          "color": {
            "mode": "thresholds"
          },
          "decimals": 0,
          "mappings": [
            {
              "options": {
                "match": "null",
                "result": {
                  "text": "N/A"
                }
              },
              "type": "special"
            }
          ],
          "thresholds": {
            "mode": "absolute",
            "steps": [
              {
                "color": "blue"
              }
            ]
          },
          "unit": "ms"
        },
        "overrides": []
      },
      "gridPos": {
        "h": 4,
        "w": 4,
        "x": 0,
        "y": 26
      },
      "hideTimeOverride": true,
      "id": 37,
      "maxDataPoints": 100,
      "options": {
        "colorMode": "value",
        "graphMode": "none",
        "justifyMode": "auto",
        "orientation": "horizontal",
        "percentChangeColorMode": "standard",
        "reduceOptions": {
          "calcs": [
            "lastNotNull"
          ],
          "fields": "",
          "values": false
        },
        "showPercentChange": false,
        "textMode": "auto",
        "wideLayout": true
      },
      "pluginVersion": "12.3.1",
      "targets": [
        {
          "datasource": {
            "type": "grafana-postgresql-datasource",
            "uid": "pgwatch-metrics"
          },
          "format": "table",
          "metricColumn": "none",
          "rawQuery": true,
          "rawSql": "SELECT (data->>'value')::float8 AS value\nFROM settings_num\nWHERE dbname = '$dbname'\n  AND tag_data->>'name' = 'statement_timeout'\n  AND $__timeFilter(time)\nORDER BY time DESC LIMIT 1",
          "refId": "A"
        }
      ],
      "timeFrom": "6h",
      "title": "Statement Timeout",
      "type": "stat"
    },
    {
      "datasource": {
        "type": "grafana-postgresql-datasource",
        "uid": "pgwatch-metrics"
      },
      "description": "",
      "fieldConfig": {
        "defaults": {
          "color": {
            "mode": "thresholds"
          },
          "decimals": 0,
          "mappings": [
            {
              "options": {
                "match": "null",
                "result": {
                  "text": "N/A"
                }
              },
              "type": "special"
            }
          ],
          "thresholds": {
            "mode": "absolute",
            "steps": [
              {
                "color": "blue"
              }
            ]
          },
          "unit": "ms"
        },
        "overrides": []
      },
      "gridPos": {
        "h": 4,
        "w": 4,
        "x": 4,
        "y": 26
      },
      "hideTimeOverride": true,
      "id": 38,
      "maxDataPoints": 100,
      "options": {
        "colorMode": "value",
        "graphMode": "none",
        "justifyMode": "auto",
        "orientation": "horizontal",
        "percentChangeColorMode": "standard",
        "reduceOptions": {
          "calcs": [
            "lastNotNull"
          ],
          "fields": "",
          "values": false
        },
        "showPercentChange": false,
        "textMode": "auto",
        "wideLayout": true
      },
      "pluginVersion": "12.3.1",
      "targets": [
        {
          "datasource": {
            "type": "grafana-postgresql-datasource",
            "uid": "pgwatch-metrics"
          },
          "format": "table",
          "metricColumn": "none",
          "rawQuery": true,
          "rawSql": "SELECT (data->>'value')::float8 AS value\nFROM settings_num\nWHERE dbname = '$dbname'\n  AND tag_data->>'name' = 'lock_timeout'\n  AND $__timeFilter(time)\nORDER BY time DESC LIMIT 1",
          "refId": "A"
        }
      ],
      "timeFrom": "6h",
      "title": "Lock Timeout",
      "type": "stat"
    },
    {
      "datasource": {
        "type": "grafana-postgresql-datasource",
        "uid": "pgwatch-metrics"
      },
      "description": "",
      "fieldConfig": {
        "defaults": {
          "color": {
            "mode": "thresholds"
          },
          "decimals": 0,
          "mappings": [
            {
              "options": {
                "match": "null",
                "result": {
                  "text": "N/A"
                }
              },
              "type": "special"
            }
          ],
          "thresholds": {
            "mode": "absolute",
            "steps": [
              {
                "color": "blue"
              }
            ]
          },
          "unit": "ms"
        },
        "overrides": []
      },
      "gridPos": {
        "h": 4,
        "w": 4,
        "x": 8,
        "y": 26
      },
      "hideTimeOverride": true,
      "id": 39,
      "maxDataPoints": 100,
      "options": {
        "colorMode": "value",
        "graphMode": "none",
        "justifyMode": "auto",
        "orientation": "horizontal",
        "percentChangeColorMode": "standard",
        "reduceOptions": {
          "calcs": [
            "lastNotNull"
          ],
          "fields": "",
          "values": false
        },
        "showPercentChange": false,
        "textMode": "auto",
        "wideLayout": true
      },
      "pluginVersion": "12.3.1",
      "targets": [
        {
          "datasource": {
            "type": "grafana-postgresql-datasource",
            "uid": "pgwatch-metrics"
          },
          "format": "table",
          "metricColumn": "none",
          "rawQuery": true,
          "rawSql": "SELECT (data->>'value')::float8 AS value\nFROM settings_num\nWHERE dbname = '$dbname'\n  AND tag_data->>'name' = 'deadlock_timeout'\n  AND $__timeFilter(time)\nORDER BY time DESC LIMIT 1",
          "refId": "A"
        }
      ],
      "timeFrom": "6h",
      "title": "Deadlock Timeout",
      "type": "stat"
    },
    {
      "datasource": {
        "type": "grafana-postgresql-datasource",
        "uid": "pgwatch-metrics"
      },
      "description": "",
      "fieldConfig": {
        "defaults": {
          "color": {
            "mode": "thresholds"
          },
          "decimals": 0,
          "mappings": [
            {
              "options": {
                "match": "null",
                "result": {
                  "text": "N/A"
                }
              },
              "type": "special"
            }
          ],
          "thresholds": {
            "mode": "absolute",
            "steps": [
              {
                "color": "blue"
              }
            ]
          },
          "unit": "none"
        },
        "overrides": []
      },
      "gridPos": {
        "h": 4,
        "w": 4,
        "x": 12,
        "y": 26
      },
      "hideTimeOverride": true,
      "id": 40,
      "maxDataPoints": 100,
      "options": {
        "colorMode": "value",
        "graphMode": "none",
        "justifyMode": "auto",
        "orientation": "horizontal",
        "percentChangeColorMode": "standard",
        "reduceOptions": {
          "calcs": [
            "lastNotNull"
          ],
          "fields": "",
          "values": false
        },
        "showPercentChange": false,
        "textMode": "auto",
        "wideLayout": true
      },
      "pluginVersion": "12.3.1",
      "targets": [
        {
          "datasource": {
            "type": "grafana-postgresql-datasource",
            "uid": "pgwatch-metrics"
          },
          "format": "table",
          "metricColumn": "none",
          "rawQuery": true,
          "rawSql": "SELECT (data->>'value')::float8 AS value\nFROM settings_num\nWHERE dbname = '$dbname'\n  AND tag_data->>'name' = 'max_prepared_transactions'\n  AND $__timeFilter(time)\nORDER BY time DESC LIMIT 1",
          "refId": "A"
        }
      ],
      "timeFrom": "6h",
      "title": "Max Prepared Transactions",
      "type": "stat"
    },
    {
      "datasource": {
        "type": "grafana-postgresql-datasource",
        "uid": "pgwatch-metrics"
      },
      "description": "",
      "fieldConfig": {
        "defaults": {
          "color": {
            "mode": "thresholds"
          },
          "decimals": 0,
          "mappings": [
            {
              "options": {
                "0": {
                  "color": "dark-red",
                  "index": 0,
                  "text": "off"
                }
              },
              "type": "value"
            },
            {
              "options": {
                "1": {
                  "color": "dark-green",
                  "index": 1,
                  "text": "on"
                }
              },
              "type": "value"
            },
            {
              "options": {
                "match": "null",
                "result": {
                  "text": "N/A"
                }
              },
              "type": "special"
            }
          ],
          "thresholds": {
            "mode": "absolute",
            "steps": [
              {
                "color": "#d44a3a",
                "value": null
              },
              {
                "color": "#299c46",
                "value": 1
              }
            ]
          },
          "unit": "none"
        },
        "overrides": []
      },
      "gridPos": {
        "h": 4,
        "w": 4,
        "x": 16,
        "y": 26
      },
      "hideTimeOverride": true,
      "id": 41,
      "maxDataPoints": 100,
      "options": {
        "colorMode": "value",
        "graphMode": "none",
        "justifyMode": "auto",
        "orientation": "horizontal",
        "percentChangeColorMode": "standard",
        "reduceOptions": {
          "calcs": [
            "lastNotNull"
          ],
          "fields": "",
          "values": false
        },
        "showPercentChange": false,
        "textMode": "auto",
        "wideLayout": true
      },
      "pluginVersion": "12.3.1",
      "targets": [
        {
          "datasource": {
            "type": "grafana-postgresql-datasource",
            "uid": "pgwatch-metrics"
          },
          "format": "table",
          "metricColumn": "none",
          "rawQuery": true,
          "rawSql": "SELECT (data->>'value')::float8 AS value\nFROM settings_num\nWHERE dbname = '$dbname'\n  AND tag_data->>'name' = 'jit'\n  AND $__timeFilter(time)\nORDER BY time DESC LIMIT 1",
          "refId": "A"
        }
      ],
      "timeFrom": "6h",
      "title": "JIT",
      "type": "stat"
    },
    {
      "datasource": {
        "type": "grafana-postgresql-datasource",
        "uid": "pgwatch-metrics"
      },
      "description": "0 = log all; -1 = disabled",
      "fieldConfig": {
        "defaults": {
          "color": {
            "mode": "thresholds"
          },
          "decimals": 0,
          "mappings": [
            {
              "options": {
                "match": "null",
                "result": {
                  "text": "N/A"
                }
              },
              "type": "special"
            }
          ],
          "thresholds": {
            "mode": "absolute",
            "steps": [
              {
                "color": "blue"
              }
            ]
          },
          "unit": "ms"
        },
        "overrides": []
      },
      "gridPos": {
        "h": 4,
        "w": 4,
        "x": 20,
        "y": 26
      },
      "hideTimeOverride": true,
      "id": 42,
      "maxDataPoints": 100,
      "options": {
        "colorMode": "value",
        "graphMode": "none",
        "justifyMode": "auto",
        "orientation": "horizontal",
        "percentChangeColorMode": "standard",
        "reduceOptions": {
          "calcs": [
            "lastNotNull"
          ],
          "fields": "",
          "values": false
        },
        "showPercentChange": false,
        "textMode": "auto",
        "wideLayout": true
      },
      "pluginVersion": "12.3.1",
      "targets": [
        {
          "datasource": {
            "type": "grafana-postgresql-datasource",
            "uid": "pgwatch-metrics"
          },
          "format": "table",
          "metricColumn": "none",
          "rawQuery": true,
          "rawSql": "SELECT (data->>'value')::float8 AS value\nFROM settings_num\nWHERE dbname = '$dbname'\n  AND tag_data->>'name' = 'log_autovacuum_min_duration'\n  AND $__timeFilter(time)\nORDER BY time DESC LIMIT 1",
          "refId": "A"
        }
      ],
      "timeFrom": "6h",
      "title": "Log Autovacuum Min Duration",
      "type": "stat"
    },
    {
      "collapsed": false,
      "gridPos": {
        "h": 1,
        "w": 24,
        "x": 0,
        "y": 30
      },
      "id": 43,
      "panels": [],
      "title": "All Settings",
      "type": "row"
    },
    {
      "datasource": {
        "type": "grafana-postgresql-datasource",
        "uid": "pgwatch-metrics"
      },
      "description": "All numeric settings from the latest snapshot. One row per setting.",
      "fieldConfig": {
        "defaults": {
          "custom": {
            "align": "auto",
            "cellOptions": {
              "type": "auto"
            },
            "inspect": false
          },
          "mappings": [],
          "thresholds": {
            "mode": "absolute",
            "steps": [
              {
                "color": "green"
              }
            ]
          }
        },
        "overrides": [
          {
            "matcher": {
              "id": "byName",
              "options": "name"
            },
            "properties": [
              {
                "id": "custom.width",
                "value": 350
              },
              {
                "id": "displayName",
                "value": "Setting Name"
              }
            ]
          },
          {
            "matcher": {
              "id": "byName",
              "options": "value"
            },
            "properties": [
              {
                "id": "custom.width",
                "value": 180
              },
              {
                "id": "displayName",
                "value": "Current Value"
              }
            ]
          }
        ]
      },
      "gridPos": {
        "h": 16,
        "w": 24,
        "x": 0,
        "y": 31
      },
      "id": 44,
      "options": {
        "cellHeight": "sm",
        "footer": {
          "show": false
        },
        "showHeader": true,
        "sortBy": [
          {
            "desc": false,
            "displayName": "Setting Name"
          }
        ]
      },
      "pluginVersion": "12.3.1",
      "targets": [
        {
          "datasource": {
            "type": "grafana-postgresql-datasource",
            "uid": "pgwatch-metrics"
          },
          "format": "table",
          "metricColumn": "none",
          "rawQuery": true,
          "rawSql": "SELECT\n  tag_data->>'name'    AS name,\n  (data->>'value')::float8 AS value\nFROM settings_num\nWHERE dbname = '$dbname'\n  AND time = (\n    SELECT max(time) FROM settings_num\n    WHERE dbname = '$dbname'\n      AND $__timeFilter(time)\n  )\nORDER BY name",
          "refId": "A"
        }
      ],
      "title": "All Settings (current snapshot)",
      "type": "table"
    },
    {
      "collapsed": false,
      "gridPos": {
        "h": 1,
        "w": 24,
        "x": 0,
        "y": 47
      },
      "id": 45,
      "panels": [],
      "title": "Changed Settings Detection",
      "type": "row"
    },
    {
      "datasource": {
        "type": "grafana-postgresql-datasource",
        "uid": "pgwatch-metrics"
      },
      "description": "Settings that took more than one distinct numeric value within the selected time window.",
      "fieldConfig": {
        "defaults": {
          "custom": {
            "align": "auto",
            "cellOptions": {
              "type": "auto"
            },
            "inspect": false
          },
          "mappings": [],
          "thresholds": {
            "mode": "absolute",
            "steps": [
              {
                "color": "yellow"
              }
            ]
          }
        },
        "overrides": [
          {
            "matcher": {
              "id": "byName",
              "options": "name"
            },
            "properties": [
              {
                "id": "custom.width",
                "value": 320
              },
              {
                "id": "displayName",
                "value": "Setting Name"
              }
            ]
          },
          {
            "matcher": {
              "id": "byName",
              "options": "distinct_values"
            },
            "properties": [
              {
                "id": "displayName",
                "value": "# Distinct Values"
              },
              {
                "id": "custom.width",
                "value": 140
              }
            ]
          },
          {
            "matcher": {
              "id": "byName",
              "options": "min_value"
            },
            "properties": [
              {
                "id": "displayName",
                "value": "Min Value"
              },
              {
                "id": "custom.width",
                "value": 120
              }
            ]
          },
          {
            "matcher": {
              "id": "byName",
              "options": "max_value"
            },
            "properties": [
              {
                "id": "displayName",
                "value": "Max Value"
              },
              {
                "id": "custom.width",
                "value": 120
              }
            ]
          }
        ]
      },
      "gridPos": {
        "h": 10,
        "w": 12,
        "x": 0,
        "y": 48
      },
      "id": 46,
      "options": {
        "cellHeight": "sm",
        "footer": {
          "show": false
        },
        "showHeader": true,
        "sortBy": [
          {
            "desc": false,
            "displayName": "Setting Name"
          }
        ]
      },
      "pluginVersion": "12.3.1",
      "targets": [
        {
          "datasource": {
            "type": "grafana-postgresql-datasource",
            "uid": "pgwatch-metrics"
          },
          "format": "table",
          "metricColumn": "none",
          "rawQuery": true,
          "rawSql": "SELECT\n  tag_data->>'name'                          AS name,\n  count(DISTINCT (data->>'value')::float8)   AS distinct_values,\n  min((data->>'value')::float8)              AS min_value,\n  max((data->>'value')::float8)              AS max_value\nFROM settings_num\nWHERE dbname = '$dbname'\n  AND $__timeFilter(time)\nGROUP BY 1\nHAVING count(DISTINCT (data->>'value')::float8) > 1\nORDER BY 1",
          "refId": "A"
        }
      ],
      "title": "Settings Changed in Time Range",
      "transformations": [
        {
          "id": "merge",
          "options": {}
        }
      ],
      "type": "table"
    },
    {
      "datasource": {
        "type": "grafana-postgresql-datasource",
        "uid": "pgwatch-metrics"
      },
      "description": "Value of the selected setting over time. Choose a setting from the $setting variable.",
      "fieldConfig": {
        "defaults": {
          "color": {
            "mode": "palette-classic"
          },
          "custom": {
            "drawStyle": "line",
            "fillOpacity": 10,
            "lineWidth": 2,
            "spanNulls": false
          },
          "mappings": [],
          "thresholds": {
            "mode": "absolute",
            "steps": [
              {
                "color": "green"
              }
            ]
          }
        },
        "overrides": []
      },
      "gridPos": {
        "h": 10,
        "w": 12,
        "x": 12,
        "y": 48
      },
      "id": 47,
      "options": {
        "legend": {
          "calcs": [],
          "displayMode": "list",
          "placement": "bottom"
        },
        "tooltip": {
          "mode": "single"
        }
      },
      "pluginVersion": "12.3.1",
      "targets": [
        {
          "datasource": {
            "type": "grafana-postgresql-datasource",
            "uid": "pgwatch-metrics"
          },
          "format": "time_series",
          "metricColumn": "none",
          "rawQuery": true,
          "rawSql": "SELECT\n  time,\n  (data->>'value')::float8 AS value\nFROM settings_num\nWHERE dbname = '$dbname'\n  AND tag_data->>'name' = '$setting'\n  AND $__timeFilter(time)\nORDER BY time",
          "refId": "A",
          "timeColumn": "time"
        }
      ],
      "title": "Setting Value Over Time: $setting",
      "type": "timeseries"
    }
  ],
  "preload": false,
  "refresh": "5m",
  "schemaVersion": 41,
  "tags": [
    "pgwatch"
  ],
  "templating": {
    "list": [
      {
        "current": {},
        "datasource": {
          "type": "grafana-postgresql-datasource",
          "uid": "pgwatch-metrics"
        },
        "definition": "SELECT DISTINCT dbname FROM admin.all_distinct_dbname_metrics WHERE metric = 'settings_num' ORDER BY 1",
        "includeAll": false,
        "multi": false,
        "name": "dbname",
        "options": [],
        "query": "SELECT DISTINCT dbname FROM admin.all_distinct_dbname_metrics WHERE metric = 'settings_num' ORDER BY 1",
        "refresh": 1,
        "regex": "",
        "sort": 1,
        "type": "query"
      },
      {
        "current": {},
        "datasource": {
          "type": "grafana-postgresql-datasource",
          "uid": "pgwatch-metrics"
        },
        "definition": "SELECT DISTINCT tag_data->>'name' FROM settings_num WHERE dbname = '$dbname' AND time > now() - '24h'::interval ORDER BY 1",
        "label": "Setting",
        "includeAll": false,
        "multi": false,
        "name": "setting",
        "options": [],
        "query": "SELECT DISTINCT tag_data->>'name' FROM settings_num WHERE dbname = '$dbname' AND time > now() - '24h'::interval ORDER BY 1",
        "refresh": 1,
        "regex": "",
        "sort": 1,
        "type": "query"
      }
    ]
  },
  "time": {
    "from": "now-6h",
    "to": "now"
  },
  "timepicker": {},
  "timezone": "",
  "title": "Settings Overview",
  "uid": "settings-num-postgres",
  "version": 1
}